ofxstatement_paypal-2.1.2-py3.10-nspkg.pth
ofxstatement/plugins/paypal.py
ofxstatement_paypal-2.1.2.dist-info/LICENSE
ofxstatement_paypal-2.1.2.dist-info/METADATA
ofxstatement_paypal-2.1.2.dist-info/WHEEL
ofxstatement_paypal-2.1.2.dist-info/entry_points.txt
ofxstatement_paypal-2.1.2.dist-info/namespace_packages.txt
ofxstatement_paypal-2.1.2.dist-info/top_level.txt
ofxstatement_paypal-2.1.2.dist-info/zip-safe
ofxstatement_paypal-2.1.2.dist-info/RECORD
