Metadata-Version: 2.1
Name: ofxstatement-paypal
Version: 2.1.2
Summary: ofxstatement plugins for paypal
Home-page: https://github.com/EtsBiz4africa/ofxstatement-paypal
Author: Business Solutions For Africa
Author-email: info@biz-4-africa.com
License: Apache License 2.0
Keywords: ofx,ofxstatement,paypal
Classifier: Development Status :: 3 - Alpha
Classifier: Programming Language :: Python :: 3
Classifier: Natural Language :: English
Classifier: Topic :: Office/Business :: Financial :: Accounting
Classifier: Topic :: Utilities
Classifier: Environment :: Console
Classifier: Operating System :: OS Independent
License-File: LICENSE
Requires-Dist: ofxstatement
